optbuild.py
optbuild-0.2.1.dist-info/METADATA
optbuild-0.2.1.dist-info/RECORD
optbuild-0.2.1.dist-info/WHEEL
optbuild-0.2.1.dist-info/top_level.txt
optbuild-0.2.1.dist-info/zip-safe
