Metadata-Version: 2.1
Name: optbuild
Version: 0.2.1
Summary: build command lines for external programs
Home-page: http://noble.gs.washington.edu/~mmh1/software/optbuild/
Author: Michael M. Hoffman
Author-email: mmh1@uw.edu
License: GNU GPLv2
Download-URL: http://noble.gs.washington.edu/~mmh1/software/optbuild/optbuild-0.2.1.tar.gz
Platform: UNKNOWN
Classifier: Natural Language :: English
Classifier: Programming Language :: Python
Requires-Dist: autolog (>=0.2.0)
Requires-Dist: six
